{
  "config": {
    "middleware": [
      "common",
      "staticAuth",
      "staticFiles",
      "auth",
      "bt"
    ],
    "coreMiddleware": [
      "meta",
      "siteFile",
      "notfound",
      "static",
      "bodyParser",
      "overrideMethod",
      "session",
      "securities",
      "multipart",
      "eggLoaderTrace",
      "teggRootProto",
      "teggCtxLifecycleMiddleware"
    ],
    "session": {
      "key": "EGG_SESS",
      "maxAge": 86400000,
      "autoCommit": true,
      "overwrite": true,
      "httpOnly": true,
      "signed": true,
      "rolling": false,
      "renew": false,
      "encode": "<Function anonymous>",
      "decode": "<Function anonymous>",
      "logValue": true,
      "genid": "<Function anonymous>"
    },
    "security": {
      "domainWhiteList": [],
      "protocolWhiteList": [],
      "defaultMiddleware": [
        "csrf",
        "hsts",
        "methodnoallow",
        "noopen",
        "nosniff",
        "csp",
        "xssProtection",
        "xframe",
        "dta"
      ],
      "csrf": {
        "enable": false,
        "type": "ctoken",
        "ignoreJSON": false,
        "cookieName": "csrfToken",
        "sessionName": "csrfToken",
        "headerName": "x-csrf-token",
        "bodyName": "_csrf",
        "queryName": "_csrf",
        "rotateWhenInvalid": false,
        "useSession": false,
        "supportedRequests": [
          {
            "path": {},
            "methods": [
              "POST",
              "PATCH",
              "DELETE",
              "PUT",
              "CONNECT"
            ]
          }
        ],
        "refererWhiteList": [],
        "cookieOptions": {
          "signed": false,
          "httpOnly": false,
          "overwrite": true
        }
      },
      "xframe": {
        "enable": true,
        "value": "SAMEORIGIN",
        "matching": "<Function anonymous>"
      },
      "hsts": {
        "enable": false,
        "maxAge": 31536000,
        "includeSubdomains": false
      },
      "methodnoallow": {
        "enable": true,
        "matching": "<Function anonymous>"
      },
      "noopen": {
        "enable": true,
        "matching": "<Function anonymous>"
      },
      "nosniff": {
        "enable": true,
        "matching": "<Function anonymous>"
      },
      "xssProtection": {
        "enable": true,
        "value": "1; mode=block",
        "matching": "<Function anonymous>"
      },
      "csp": {
        "enable": false,
        "policy": {}
      },
      "referrerPolicy": {
        "enable": false,
        "value": "no-referrer-when-downgrade"
      },
      "dta": {
        "enable": true,
        "matching": "<Function anonymous>"
      },
      "ssrf": {}
    },
    "helper": {
      "shtml": {}
    },
    "jsonp": {
      "limit": 50,
      "callback": [
        "_callback",
        "callback"
      ],
      "csrf": false
    },
    "onerror": {
      "errorPageUrl": "",
      "templatePath": "/Users/bt.cn/project/linglongos/node_modules/.pnpm/@eggjs+onerror@3.0.0/node_modules/@eggjs/onerror/dist/commonjs/lib/onerror_page.mustache.html"
    },
    "i18n": {
      "defaultLocale": "en-us",
      "dirs": [
        "/Users/bt.cn/project/linglongos/node_modules/.pnpm/@eggjs+session@4.0.1/node_modules/@eggjs/session/dist/commonjs/config/locales",
        "/Users/bt.cn/project/linglongos/node_modules/.pnpm/@eggjs+security@4.0.1/node_modules/@eggjs/security/dist/commonjs/config/locales",
        "/Users/bt.cn/project/linglongos/node_modules/.pnpm/@eggjs+jsonp@3.0.0/node_modules/@eggjs/jsonp/dist/commonjs/config/locales",
        "/Users/bt.cn/project/linglongos/node_modules/.pnpm/@eggjs+onerror@3.0.0/node_modules/@eggjs/onerror/dist/commonjs/config/locales",
        "/Users/bt.cn/project/linglongos/node_modules/.pnpm/@eggjs+i18n@3.0.1/node_modules/@eggjs/i18n/dist/commonjs/config/locales",
        "/Users/bt.cn/project/linglongos/node_modules/.pnpm/@eggjs+watcher@4.0.4/node_modules/@eggjs/watcher/dist/commonjs/config/locales",
        "/Users/bt.cn/project/linglongos/node_modules/.pnpm/@eggjs+schedule@5.0.2/node_modules/@eggjs/schedule/dist/commonjs/config/locales",
        "/Users/bt.cn/project/linglongos/node_modules/.pnpm/@eggjs+multipart@4.0.0/node_modules/@eggjs/multipart/dist/commonjs/config/locales",
        "/Users/bt.cn/project/linglongos/node_modules/.pnpm/@eggjs+development@4.0.0/node_modules/@eggjs/development/dist/commonjs/config/locales",
        "/Users/bt.cn/project/linglongos/node_modules/.pnpm/@eggjs+logrotator@4.1.0/node_modules/@eggjs/logrotator/dist/commonjs/config/locales",
        "/Users/bt.cn/project/linglongos/node_modules/.pnpm/@eggjs+static@3.0.0/node_modules/@eggjs/static/dist/commonjs/config/locales",
        "/Users/bt.cn/project/linglongos/node_modules/.pnpm/@eggjs+view@3.0.1/node_modules/@eggjs/view/dist/commonjs/config/locales",
        "/Users/bt.cn/project/linglongos/apps/api/node_modules/@eggjs/tegg-config/config/locales",
        "/Users/bt.cn/project/linglongos/apps/api/node_modules/@eggjs/tegg-plugin/config/locales",
        "/Users/bt.cn/project/linglongos/apps/api/node_modules/@eggjs/tegg-controller-plugin/config/locales",
        "/Users/bt.cn/project/linglongos/apps/api/node_modules/@eggjs/tegg-schedule-plugin/config/locales",
        "/Users/bt.cn/project/linglongos/apps/api/node_modules/@eggjs/tegg-eventbus-plugin/config/locales",
        "/Users/bt.cn/project/linglongos/apps/api/node_modules/@eggjs/tegg-aop-plugin/config/locales",
        "/Users/bt.cn/project/linglongos/apps/api/node_modules/@eggjs/tracer/dist/commonjs/config/locales",
        "/Users/bt.cn/project/linglongos/node_modules/.pnpm/egg@4.0.10/node_modules/egg/dist/commonjs/config/locales",
        "/Users/bt.cn/project/linglongos/apps/api/config/locales"
      ],
      "queryField": "locale",
      "cookieField": "locale",
      "cookieDomain": "",
      "cookieMaxAge": 31557600000,
      "localeAlias": {},
      "writeCookie": true
    },
    "watcher": {
      "type": "development",
      "eventSources": {
        "default": "/Users/bt.cn/project/linglongos/node_modules/.pnpm/@eggjs+watcher@4.0.4/node_modules/@eggjs/watcher/dist/commonjs/lib/event-sources/default",
        "development": "/Users/bt.cn/project/linglongos/node_modules/.pnpm/@eggjs+watcher@4.0.4/node_modules/@eggjs/watcher/dist/commonjs/lib/event-sources/development"
      }
    },
    "customLogger": {
      "scheduleLogger": {
        "consoleLevel": "NONE",
        "file": "egg-schedule.log"
      }
    },
    "schedule": {
      "directory": []
    },
    "multipart": {
      "mode": "file",
      "autoFields": false,
      "defaultCharset": "utf8",
      "defaultParamCharset": "utf8",
      "fieldNameSize": 100,
      "fieldSize": 102400,
      "fields": 10,
      "fileSize": 10485760,
      "files": 10,
      "fileExtensions": [],
      "whitelist": null,
      "allowArrayField": false,
      "tmpdir": "/var/folders/6l/ldtm6tb96qb4jr0pn63zcsmh0000gn/T/egg-multipart-tmp/@linglongos/api",
      "cleanSchedule": {
        "cron": "0 30 4 * * *",
        "disable": false
      },
      "checkFile": "<Function anonymous>"
    },
    "development": {
      "watchDirs": [],
      "ignoreDirs": [],
      "fastReady": false,
      "reloadOnDebug": true,
      "overrideDefault": false,
      "overrideIgnore": false
    },
    "logrotator": {
      "disableRotateByDay": false,
      "filesRotateByHour": null,
      "hourDelimiter": "-",
      "filesRotateBySize": null,
      "maxFileSize": 52428800,
      "maxFiles": 10,
      "rotateDuration": 60000,
      "maxDays": 31,
      "gzip": false
    },
    "static": {
      "prefix": "/public/",
      "dir": "/Users/bt.cn/project/linglongos/apps/api/app/public",
      "dynamic": true,
      "preload": false,
      "buffer": false,
      "maxFiles": 1000
    },
    "view": {
      "root": "/Users/bt.cn/project/linglongos/apps/api/app/view",
      "cache": false,
      "defaultExtension": ".html",
      "defaultViewEngine": "",
      "mapping": {}
    },
    "mcp": {
      "sseInitPath": "/mcp/sse",
      "sseMessagePath": "/mcp/message",
      "streamPath": "/mcp/stream",
      "statelessStreamPath": "/mcp/stateless/stream",
      "sessionIdGenerator": "<Function randomUUID>",
      "hooks": []
    },
    "tracer": {
      "Class": "<Class Tracer>"
    },
    "env": "local",
    "name": "@linglongos/api",
    "keys": "<String len: 34>",
    "cookies": {},
    "proxy": false,
    "maxIpsCount": 0,
    "maxProxyCount": 0,
    "protocolHeaders": "x-forwarded-proto",
    "ipHeaders": "x-forwarded-for",
    "hostHeaders": "",
    "pkg": {
      "name": "@linglongos/api",
      "version": "1.0.0",
      "description": "",
      "private": true,
      "egg": {
        "typescript": true
      },
      "scripts": {
        "start": "eggctl start --daemon --title=egg-server-api --baseDir=./dist",
        "stop": "eggctl stop --title=egg-server-api",
        "dev": "egg-bin dev",
        "test:local": "egg-bin test",
        "pretest": "npm run clean && npm run lint -- --fix",
        "test": "egg-bin test",
        "preci": "npm run clean && npm run lint",
        "ci": "egg-bin cov",
        "postci": "npm run prepublishOnly && npm start && npm stop && npm run clean",
        "lint": "eslint . --ext .ts --cache",
        "tsc": "tsc",
        "clean": "tsc -b --clean && rm -rf dist",
        "export:openapi": "node ./scripts/export-openapi.js",
        "migrate:to-sqlite": "node ./scripts/run-migration.js",
        "prepublishOnly": "npm run clean && npm run tsc"
      },
      "dependencies": {
        "@eggjs/scripts": "^4.0.0",
        "@eggjs/tegg": "^3.5.2",
        "@eggjs/tegg-aop-plugin": "^3.5.2",
        "@eggjs/tegg-config": "^3.5.2",
        "@eggjs/tegg-controller-plugin": "^3.5.2",
        "@eggjs/tegg-eventbus-plugin": "^3.5.2",
        "@eggjs/tegg-plugin": "^3.5.2",
        "@eggjs/tegg-schedule-plugin": "^3.5.2",
        "@eggjs/tracer": "^3.0.0",
        "axios": "^1.7.7",
        "better-sqlite3": "^9.6.0",
        "egg": "^4.0.0",
        "md5": "^2.3.0",
        "speakeasy": "^2.0.0",
        "sqlite3": "^5.1.7"
      },
      "devDependencies": {
        "@eggjs/bin": "7",
        "@eggjs/mock": "6",
        "@eggjs/tsconfig": "1",
        "@types/mocha": "10",
        "@types/node": "22",
        "eslint": "8",
        "eslint-config-egg": "14",
        "typescript": "5"
      },
      "engines": {
        "node": ">=20.18.1"
      },
      "repository": {
        "type": "git",
        "url": ""
      },
      "author": "",
      "license": "MIT"
    },
    "baseDir": "/Users/bt.cn/project/linglongos/apps/api",
    "HOME": "/Users/bt.cn",
    "rundir": "/Users/bt.cn/project/linglongos/apps/api/run",
    "dump": {
      "ignore": "<Set>",
      "timing": {
        "slowBootActionMinDuration": 5000
      }
    },
    "confusedConfigurations": {
      "bodyparser": "bodyParser",
      "notFound": "notfound",
      "sitefile": "siteFile",
      "middlewares": "middleware",
      "httpClient": "httpclient"
    },
    "notfound": {
      "enable": true,
      "pageUrl": ""
    },
    "siteFile": {
      "enable": true,
      "/favicon.ico": "file:///Users/bt.cn/project/linglongos/node_modules/.pnpm/egg@4.0.10/node_modules/egg/dist/commonjs/config/favicon.png",
      "cacheControl": "public, max-age=2592000"
    },
    "bodyParser": {
      "enable": true,
      "encoding": "utf8",
      "formLimit": "1mb",
      "jsonLimit": "1mb",
      "textLimit": "1mb",
      "strict": true,
      "queryString": {
        "arrayLimit": 100,
        "depth": 5,
        "parameterLimit": 1000
      },
      "onProtoPoisoning": "error",
      "returnRawBody": true
    },
    "logger": {
      "dir": "/Users/bt.cn/project/linglongos/apps/api/logs/@linglongos/api",
      "encoding": "utf8",
      "env": "local",
      "level": "INFO",
      "consoleLevel": "INFO",
      "disableConsoleAfterReady": false,
      "outputJSON": false,
      "buffer": true,
      "appLogName": "@linglongos/api-web.log",
      "coreLogName": "egg-web.log",
      "agentLogName": "egg-agent.log",
      "errorLogName": "common-error.log",
      "coreLogger": {
        "consoleLevel": "WARN"
      },
      "allowDebugAtProd": false,
      "enableFastContextLogger": true
    },
    "httpclient": {
      "request": {
        "timeout": 5000
      }
    },
    "meta": {
      "enable": true,
      "logging": false
    },
    "workerStartTimeout": 600000,
    "serverTimeout": null,
    "cluster": {
      "listen": {
        "path": "",
        "port": 7001,
        "hostname": ""
      }
    },
    "clusterClient": {
      "maxWaitTime": 60000,
      "responseTimeout": 60000
    },
    "staticAuth": {},
    "staticFiles": {
      "root": "/Users/bt.cn/project/linglongos/apps/api/app/public",
      "allowedExtensions": [
        ".html",
        ".htm",
        ".css",
        ".js",
        ".mjs",
        ".json",
        ".xml",
        ".txt",
        ".md",
        ".png",
        ".jpg",
        ".jpeg",
        ".gif",
        ".svg",
        ".ico",
        ".webp",
        ".woff",
        ".woff2",
        ".ttf",
        ".eot",
        ".pdf",
        ".zip",
        ".tar",
        ".gz"
      ],
      "maxAge": 86400,
      "gzip": true,
      "etag": true,
      "match": [
        {}
      ]
    },
    "auth": {
      "ignore": [
        {},
        {},
        {},
        {},
        {}
      ]
    },
    "bt": {
      "match": [
        {}
      ]
    },
    "common": {},
    "sqlite": {
      "path": "/Users/bt.cn/project/linglongos/apps/api/data/api.db"
    },
    "bizConfig": {
      "sourceUrl": "https://github.com/eggjs/examples/tree/master/@linglongos/api"
    },
    "coreMiddlewares": "~config~coreMiddleware",
    "appMiddleware": "~config~middleware",
    "appMiddlewares": "~config~middleware"
  },
  "plugins": {
    "onerror": {
      "enable": true,
      "package": "@eggjs/onerror",
      "name": "onerror",
      "dependencies": [],
      "optionalDependencies": [
        "jsonp"
      ],
      "env": [],
      "from": "/Users/bt.cn/project/linglongos/node_modules/.pnpm/egg@4.0.10/node_modules/egg/dist/commonjs/config/plugin.js",
      "path": "/Users/bt.cn/project/linglongos/node_modules/.pnpm/@eggjs+onerror@3.0.0/node_modules/@eggjs/onerror/dist/commonjs",
      "version": "3.0.0"
    },
    "session": {
      "enable": true,
      "package": "@eggjs/session",
      "name": "session",
      "dependencies": [],
      "optionalDependencies": [],
      "env": [],
      "from": "/Users/bt.cn/project/linglongos/node_modules/.pnpm/egg@4.0.10/node_modules/egg/dist/commonjs/config/plugin.js",
      "path": "/Users/bt.cn/project/linglongos/node_modules/.pnpm/@eggjs+session@4.0.1/node_modules/@eggjs/session/dist/commonjs",
      "version": "4.0.1"
    },
    "i18n": {
      "enable": true,
      "package": "@eggjs/i18n",
      "name": "i18n",
      "dependencies": [],
      "optionalDependencies": [],
      "env": [],
      "from": "/Users/bt.cn/project/linglongos/node_modules/.pnpm/egg@4.0.10/node_modules/egg/dist/commonjs/config/plugin.js",
      "path": "/Users/bt.cn/project/linglongos/node_modules/.pnpm/@eggjs+i18n@3.0.1/node_modules/@eggjs/i18n/dist/commonjs",
      "version": "3.0.1"
    },
    "watcher": {
      "enable": true,
      "package": "@eggjs/watcher",
      "name": "watcher",
      "dependencies": [],
      "optionalDependencies": [],
      "env": [],
      "from": "/Users/bt.cn/project/linglongos/node_modules/.pnpm/egg@4.0.10/node_modules/egg/dist/commonjs/config/plugin.js",
      "path": "/Users/bt.cn/project/linglongos/node_modules/.pnpm/@eggjs+watcher@4.0.4/node_modules/@eggjs/watcher/dist/commonjs",
      "version": "4.0.4",
      "dependents": [
        "development"
      ]
    },
    "multipart": {
      "enable": true,
      "package": "@eggjs/multipart",
      "name": "multipart",
      "dependencies": [],
      "optionalDependencies": [
        "schedule"
      ],
      "env": [],
      "from": "/Users/bt.cn/project/linglongos/node_modules/.pnpm/egg@4.0.10/node_modules/egg/dist/commonjs/config/plugin.js",
      "path": "/Users/bt.cn/project/linglongos/node_modules/.pnpm/@eggjs+multipart@4.0.0/node_modules/@eggjs/multipart/dist/commonjs",
      "version": "4.0.0"
    },
    "security": {
      "enable": true,
      "package": "@eggjs/security",
      "name": "security",
      "dependencies": [],
      "optionalDependencies": [
        "session"
      ],
      "env": [],
      "from": "/Users/bt.cn/project/linglongos/node_modules/.pnpm/egg@4.0.10/node_modules/egg/dist/commonjs/config/plugin.js",
      "path": "/Users/bt.cn/project/linglongos/node_modules/.pnpm/@eggjs+security@4.0.1/node_modules/@eggjs/security/dist/commonjs",
      "version": "4.0.1"
    },
    "development": {
      "enable": true,
      "package": "@eggjs/development",
      "name": "development",
      "dependencies": [
        "watcher"
      ],
      "optionalDependencies": [],
      "env": [
        "local"
      ],
      "from": "/Users/bt.cn/project/linglongos/node_modules/.pnpm/egg@4.0.10/node_modules/egg/dist/commonjs/config/plugin.js",
      "path": "/Users/bt.cn/project/linglongos/node_modules/.pnpm/@eggjs+development@4.0.0/node_modules/@eggjs/development/dist/commonjs",
      "version": "4.0.0"
    },
    "logrotator": {
      "enable": true,
      "package": "@eggjs/logrotator",
      "name": "logrotator",
      "dependencies": [
        "schedule"
      ],
      "optionalDependencies": [],
      "env": [],
      "from": "/Users/bt.cn/project/linglongos/node_modules/.pnpm/egg@4.0.10/node_modules/egg/dist/commonjs/config/plugin.js",
      "path": "/Users/bt.cn/project/linglongos/node_modules/.pnpm/@eggjs+logrotator@4.1.0/node_modules/@eggjs/logrotator/dist/commonjs",
      "version": "4.1.0"
    },
    "schedule": {
      "enable": true,
      "package": "@eggjs/schedule",
      "name": "schedule",
      "dependencies": [],
      "optionalDependencies": [],
      "env": [],
      "from": "/Users/bt.cn/project/linglongos/node_modules/.pnpm/egg@4.0.10/node_modules/egg/dist/commonjs/config/plugin.js",
      "path": "/Users/bt.cn/project/linglongos/node_modules/.pnpm/@eggjs+schedule@5.0.2/node_modules/@eggjs/schedule/dist/commonjs",
      "version": "5.0.2",
      "dependents": [
        "logrotator",
        "teggSchedule"
      ]
    },
    "static": {
      "enable": true,
      "package": "@eggjs/static",
      "name": "static",
      "dependencies": [],
      "optionalDependencies": [],
      "env": [],
      "from": "/Users/bt.cn/project/linglongos/node_modules/.pnpm/egg@4.0.10/node_modules/egg/dist/commonjs/config/plugin.js",
      "path": "/Users/bt.cn/project/linglongos/node_modules/.pnpm/@eggjs+static@3.0.0/node_modules/@eggjs/static/dist/commonjs",
      "version": "3.0.0"
    },
    "jsonp": {
      "enable": true,
      "package": "@eggjs/jsonp",
      "name": "jsonp",
      "dependencies": [],
      "optionalDependencies": [
        "security"
      ],
      "env": [],
      "from": "/Users/bt.cn/project/linglongos/node_modules/.pnpm/egg@4.0.10/node_modules/egg/dist/commonjs/config/plugin.js",
      "path": "/Users/bt.cn/project/linglongos/node_modules/.pnpm/@eggjs+jsonp@3.0.0/node_modules/@eggjs/jsonp/dist/commonjs",
      "version": "3.0.0"
    },
    "view": {
      "enable": true,
      "package": "@eggjs/view",
      "name": "view",
      "dependencies": [],
      "optionalDependencies": [],
      "env": [],
      "from": "/Users/bt.cn/project/linglongos/node_modules/.pnpm/egg@4.0.10/node_modules/egg/dist/commonjs/config/plugin.js",
      "path": "/Users/bt.cn/project/linglongos/node_modules/.pnpm/@eggjs+view@3.0.1/node_modules/@eggjs/view/dist/commonjs",
      "version": "3.0.1"
    },
    "tegg": {
      "enable": true,
      "package": "@eggjs/tegg-plugin",
      "name": "tegg",
      "dependencies": [
        "teggConfig"
      ],
      "optionalDependencies": [],
      "env": [],
      "from": "/Users/bt.cn/project/linglongos/apps/api/config/plugin.ts",
      "path": "/Users/bt.cn/project/linglongos/apps/api/node_modules/@eggjs/tegg-plugin",
      "version": "3.62.0",
      "dependents": [
        "teggController",
        "teggSchedule",
        "eventbusModule",
        "aopModule"
      ]
    },
    "teggConfig": {
      "enable": true,
      "package": "@eggjs/tegg-config",
      "name": "teggConfig",
      "dependencies": [],
      "optionalDependencies": [],
      "env": [],
      "from": "/Users/bt.cn/project/linglongos/apps/api/config/plugin.ts",
      "path": "/Users/bt.cn/project/linglongos/apps/api/node_modules/@eggjs/tegg-config",
      "version": "3.62.0",
      "dependents": [
        "tegg"
      ]
    },
    "teggController": {
      "enable": true,
      "package": "@eggjs/tegg-controller-plugin",
      "name": "teggController",
      "dependencies": [
        "tegg"
      ],
      "optionalDependencies": [],
      "env": [],
      "from": "/Users/bt.cn/project/linglongos/apps/api/config/plugin.ts",
      "path": "/Users/bt.cn/project/linglongos/apps/api/node_modules/@eggjs/tegg-controller-plugin",
      "version": "3.62.0"
    },
    "teggSchedule": {
      "enable": true,
      "package": "@eggjs/tegg-schedule-plugin",
      "name": "teggSchedule",
      "dependencies": [
        "tegg",
        "schedule"
      ],
      "optionalDependencies": [],
      "env": [],
      "from": "/Users/bt.cn/project/linglongos/apps/api/config/plugin.ts",
      "path": "/Users/bt.cn/project/linglongos/apps/api/node_modules/@eggjs/tegg-schedule-plugin",
      "version": "3.62.0"
    },
    "eventbusModule": {
      "enable": true,
      "package": "@eggjs/tegg-eventbus-plugin",
      "name": "eventbusModule",
      "dependencies": [
        "tegg"
      ],
      "optionalDependencies": [],
      "env": [],
      "from": "/Users/bt.cn/project/linglongos/apps/api/config/plugin.ts",
      "path": "/Users/bt.cn/project/linglongos/apps/api/node_modules/@eggjs/tegg-eventbus-plugin",
      "version": "3.62.0"
    },
    "aopModule": {
      "enable": true,
      "package": "@eggjs/tegg-aop-plugin",
      "name": "aopModule",
      "dependencies": [
        "tegg"
      ],
      "optionalDependencies": [],
      "env": [],
      "from": "/Users/bt.cn/project/linglongos/apps/api/config/plugin.ts",
      "path": "/Users/bt.cn/project/linglongos/apps/api/node_modules/@eggjs/tegg-aop-plugin",
      "version": "3.62.0"
    },
    "tracer": {
      "enable": true,
      "package": "@eggjs/tracer",
      "name": "tracer",
      "dependencies": [],
      "optionalDependencies": [],
      "env": [],
      "from": "/Users/bt.cn/project/linglongos/apps/api/config/plugin.ts",
      "path": "/Users/bt.cn/project/linglongos/apps/api/node_modules/@eggjs/tracer/dist/commonjs",
      "version": "3.0.0"
    }
  },
  "appInfo": {
    "name": "@linglongos/api",
    "baseDir": "/Users/bt.cn/project/linglongos/apps/api",
    "env": "local",
    "scope": "",
    "HOME": "/Users/bt.cn",
    "pkg": {
      "name": "@linglongos/api",
      "version": "1.0.0",
      "description": "",
      "private": true,
      "egg": {
        "typescript": true
      },
      "scripts": {
        "start": "eggctl start --daemon --title=egg-server-api --baseDir=./dist",
        "stop": "eggctl stop --title=egg-server-api",
        "dev": "egg-bin dev",
        "test:local": "egg-bin test",
        "pretest": "npm run clean && npm run lint -- --fix",
        "test": "egg-bin test",
        "preci": "npm run clean && npm run lint",
        "ci": "egg-bin cov",
        "postci": "npm run prepublishOnly && npm start && npm stop && npm run clean",
        "lint": "eslint . --ext .ts --cache",
        "tsc": "tsc",
        "clean": "tsc -b --clean && rm -rf dist",
        "export:openapi": "node ./scripts/export-openapi.js",
        "migrate:to-sqlite": "node ./scripts/run-migration.js",
        "prepublishOnly": "npm run clean && npm run tsc"
      },
      "dependencies": {
        "@eggjs/scripts": "^4.0.0",
        "@eggjs/tegg": "^3.5.2",
        "@eggjs/tegg-aop-plugin": "^3.5.2",
        "@eggjs/tegg-config": "^3.5.2",
        "@eggjs/tegg-controller-plugin": "^3.5.2",
        "@eggjs/tegg-eventbus-plugin": "^3.5.2",
        "@eggjs/tegg-plugin": "^3.5.2",
        "@eggjs/tegg-schedule-plugin": "^3.5.2",
        "@eggjs/tracer": "^3.0.0",
        "axios": "^1.7.7",
        "better-sqlite3": "^9.6.0",
        "egg": "^4.0.0",
        "md5": "^2.3.0",
        "speakeasy": "^2.0.0",
        "sqlite3": "^5.1.7"
      },
      "devDependencies": {
        "@eggjs/bin": "7",
        "@eggjs/mock": "6",
        "@eggjs/tsconfig": "1",
        "@types/mocha": "10",
        "@types/node": "22",
        "eslint": "8",
        "eslint-config-egg": "14",
        "typescript": "5"
      },
      "engines": {
        "node": ">=20.18.1"
      },
      "repository": {
        "type": "git",
        "url": ""
      },
      "author": "",
      "license": "MIT"
    },
    "root": "/Users/bt.cn/project/linglongos/apps/api"
  }
}